{"category":"Orchestration & Management","homepage_url":"https://grpc.io","id":"orchestration-management--remote-procedure-call--grpc","logo_url":"https://landscape.cncf.io/logos/91304b6bc0ca2e9107c18c43a5732879d478909b6d2761b62af2beb445829d48.svg","name":"gRPC","subcategory":"Remote Procedure Call","accepted_at":"2017-02-16","artwork_url":"https://github.com/cncf/artwork/blob/master/examples/incubating.md#grpc-logos","audits":[{"date":"2019-10-29","type":"security","url":"https://github.com/grpc/grpc/blob/master/doc/security_audit.md","vendor":"Cure53"}],"blog_url":"http://www.grpc.io/blog/","crunchbase_url":"https://www.crunchbase.com/organization/cloud-native-computing-foundation","description":"A high performance, open source universal RPC framework.","devstats_url":"https://grpc.devstats.cncf.io/","gitter_url":"https://gitter.im/grpc/grpc","incubating_at":"2017-02-16","lfx_slug":"grpc","maturity":"incubating","repositories":[{"url":"https://github.com/grpc/grpc","primary":true}],"stack_overflow_url":"https://stackoverflow.com/questions/tagged/grpc","tag":["network"],"twitter_url":"https://twitter.com/grpcio","youtube_url":"https://www.youtube.com/channel/UCrnk1HWelWnYtF78YZX80fg"}