{"category":"Orchestration & Management","homepage_url":"https://sermant.io/","id":"orchestration-management--service-mesh--sermant","logo_url":"https://landscape.cncf.io/logos/f4255f32ec6577f151f9a0335017ecd36dcf2e8b1656a558a401088eac810218.svg","name":"Sermant","subcategory":"Service Mesh","accepted_at":"2024-10-09","artwork_url":"https://github.com/cncf/artwork/tree/master/projects/sermant","crunchbase_url":"https://www.crunchbase.com/organization/cloud-native-computing-foundation","description":"Sermant a proxyless service mesh solution based on Javaagent.","devstats_url":"https://sermant.devstats.cncf.io/","lfx_slug":"sermant","maturity":"sandbox","repositories":[{"url":"https://github.com/sermant-io/Sermant","primary":true}],"tag":["network"]}