{"items":[{"category":"Wasm","homepage_url":"https://github.com/GoogleChromeLabs/asyncify","id":"wasm--tooling--asyncify","logo":"logos/8e241f1145fcf8ca479d6a65e04a1ef7e5ca9817e2d25dfe08953b649b22fb20.svg","name":"Asyncify","subcategory":"Tooling","website":"https://github.com/GoogleChromeLabs/asyncify","crunchbase_url":"https://www.crunchbase.com/organization/google","member_subcategory":"Platinum","repositories":[{"url":"https://github.com/GoogleChromeLabs/asyncify","primary":true}]},{"category":"Wasm","homepage_url":"https://github.com/WebAssembly/binaryen","id":"wasm--tooling--binaryen","logo":"logos/8e241f1145fcf8ca479d6a65e04a1ef7e5ca9817e2d25dfe08953b649b22fb20.svg","name":"Binaryen","subcategory":"Tooling","website":"https://github.com/WebAssembly/binaryen","crunchbase_url":"https://www.crunchbase.com/organization/webassembly","repositories":[{"url":"https://github.com/WebAssembly/binaryen","primary":true}]},{"category":"Wasm","homepage_url":"https://doc.rust-lang.org/cargo/","id":"wasm--tooling--cargo","logo":"logos/5918f8798f76513f485c88512efc988b122242122b8024533888b56b80a27c17.svg","name":"cargo","subcategory":"Tooling","website":"https://doc.rust-lang.org/cargo/","crunchbase_url":"https://www.crunchbase.com/organization/rust","repositories":[{"url":"https://github.com/rust-lang/cargo","primary":true}]},{"category":"Wasm","homepage_url":"https://yomaytk.github.io/elfconv-demo/","id":"wasm--tooling--elfconv","logo":"logos/d818e188fddbbb0de18bd618697014c5e9178efb284473bbb798bac6e05c40ff.svg","name":"elfconv","subcategory":"Tooling","website":"https://yomaytk.github.io/elfconv-demo/","description":"An AOT binary translator that converts Linux/ELF binaries to WebAssembly","repositories":[{"url":"https://github.com/yomaytk/elfconv","primary":true}],"unnamed_organization":true},{"category":"Wasm","homepage_url":"https://emscripten.org","id":"wasm--tooling--emscripten","logo":"logos/8e241f1145fcf8ca479d6a65e04a1ef7e5ca9817e2d25dfe08953b649b22fb20.svg","name":"emscripten","subcategory":"Tooling","website":"https://emscripten.org","crunchbase_url":"https://www.crunchbase.com/organization/mozilla","repositories":[{"url":"https://github.com/emscripten-core/emscripten","primary":true}]},{"category":"Wasm","homepage_url":"https://llvm.org","id":"wasm--tooling--llvm","logo":"logos/d6acaa26176560fe6b0045941ee100433c58d7fba443febd8bbe841c57cd1fc7.svg","name":"llvm","subcategory":"Tooling","website":"https://llvm.org","crunchbase_url":"https://www.crunchbase.com/organization/llvm-foundation","repositories":[{"url":"https://github.com/llvm/llvm-project","primary":true}]},{"category":"Wasm","homepage_url":"https://github.com/wasmerio/vscode-wasm","id":"wasm--tooling--vscode-wasm-extension","logo":"logos/a67639888ba90ab6cd5e6f94f2fd4e91c83cb3b5abbd343f6c30af0e427940d0.svg","name":"VSCode Wasm Extension","subcategory":"Tooling","website":"https://github.com/wasmerio/vscode-wasm","crunchbase_url":"https://www.crunchbase.com/organization/wasmer","repositories":[{"url":"https://github.com/wasmerio/vscode-wasm","primary":true}]},{"category":"Wasm","homepage_url":"https://github.com/WebAssembly/wabt","id":"wasm--tooling--wabt","logo":"logos/8e241f1145fcf8ca479d6a65e04a1ef7e5ca9817e2d25dfe08953b649b22fb20.svg","name":"Wabt","subcategory":"Tooling","website":"https://github.com/WebAssembly/wabt","crunchbase_url":"https://www.crunchbase.com/organization/webassembly","repositories":[{"url":"https://github.com/WebAssembly/wabt","primary":true}]},{"category":"Wasm","homepage_url":"https://github.com/wasmerio/wai","id":"wasm--tooling--wai","logo":"logos/a67639888ba90ab6cd5e6f94f2fd4e91c83cb3b5abbd343f6c30af0e427940d0.svg","name":"WAI","subcategory":"Tooling","website":"https://github.com/wasmerio/wai","crunchbase_url":"https://www.crunchbase.com/organization/wasmer","repositories":[{"url":"https://github.com/wasmerio/wai","primary":true}]},{"category":"Wasm","homepage_url":"https://rustwasm.github.io/wasm-bindgen/","id":"wasm--tooling--wasm-bindgen","logo":"logos/d7546c6180902a13f672733eb854a41e2fa8e9c92b06d58a2a6c9186ff25dd1d.svg","name":"wasm-bindgen","subcategory":"Tooling","website":"https://rustwasm.github.io/wasm-bindgen/","repositories":[{"url":"https://github.com/rustwasm/wasm-bindgen","primary":true}],"unnamed_organization":true},{"category":"Wasm","homepage_url":"https://rustwasm.github.io/wasm-pack/","id":"wasm--tooling--wasm-pack","logo":"logos/d7546c6180902a13f672733eb854a41e2fa8e9c92b06d58a2a6c9186ff25dd1d.svg","name":"wasm-pack","subcategory":"Tooling","website":"https://rustwasm.github.io/wasm-pack/","repositories":[{"url":"https://github.com/rustwasm/wasm-pack","primary":true}],"unnamed_organization":true},{"category":"Wasm","homepage_url":"https://github.com/WebAssembly/wabt/tree/main/wasm2c","id":"wasm--tooling--wasm2c","logo":"logos/12c218f7e78946a86147989264d0f0d524a946181ed1213201fb341d1cc95165.svg","name":"wasm2c","subcategory":"Tooling","website":"https://github.com/WebAssembly/wabt/tree/main/wasm2c","crunchbase_url":"https://www.crunchbase.com/organization/webassembly","repositories":[{"url":"https://github.com/WebAssembly/wabt","primary":true}]},{"category":"Wasm","homepage_url":"https://github.com/bytecodealliance/wit-bindgen","id":"wasm--tooling--wit-binddgen","logo":"logos/0bea44fa919058be29d622fabf114df380c2d7b2dee22e956e4c884a5a3045cb.svg","name":"Wit-binddgen","subcategory":"Tooling","website":"https://github.com/bytecodealliance/wit-bindgen","crunchbase_url":"https://www.crunchbase.com/organization/bytecode-alliance","repositories":[{"url":"https://github.com/bytecodealliance/wit-bindgen","primary":true}]},{"category":"Wasm","homepage_url":"https://github.com/second-state/witc","id":"wasm--tooling--witc","logo":"logos/676d1ef9b1d1440cf6271d26922cd16aa5a9d74070548ccd11c667df15d772a7.svg","name":"Witc","subcategory":"Tooling","website":"https://github.com/second-state/witc","crunchbase_url":"https://www.crunchbase.com/organization/second-state","member_subcategory":"Silver","repositories":[{"url":"https://github.com/second-state/witc","primary":true}]}]}